deathdaily.py
deathdaily-0.1.7.dist-info/METADATA
deathdaily-0.1.7.dist-info/WHEEL
deathdaily-0.1.7.dist-info/entry_points.txt
deathdaily-0.1.7.dist-info/top_level.txt
deathdaily-0.1.7.dist-info/RECORD
