Metadata-Version: 2.1
Name: deathdaily
Version: 0.1.7
Summary: A package for predicting the number of daily deaths
Home-page: https://github.com/y-takefuji/covid-19_daily_death_prediction
Author: yoshiyasu takefuji
Author-email: takefuji@keio.jp
License: UNKNOWN
Project-URL: Bug Tracker, https://github.com/y-takefuji/covid-19_daily_death_prediction
Platform: UNKNOWN
Classifier: Programming Language :: Python :: 3
Classifier: License :: OSI Approved :: MIT License
Classifier: Operating System :: OS Independent
Requires-Python: >=3.8
